pydrink/config.py
pydrink/drink.py
pydrink/git.py
pydrink/log.py
pydrink/obj.py
pydrink-0.4.0.dist-info/METADATA
pydrink-0.4.0.dist-info/WHEEL
pydrink-0.4.0.dist-info/entry_points.txt
pydrink-0.4.0.dist-info/licenses/LICENSE.txt
pydrink-0.4.0.dist-info/RECORD
