Metadata-Version: 2.4
Name: pydrink
Version: 0.4.0
Summary: Distributed Reusage of Invaluable Nerd Kit (dotfile management)
Project-URL: Repository, https://github.com/sstark/pydrink
Author-email: Sebastian Stark <sstark@mailbox.org>
License-Expression: ISC
License-File: LICENSE.txt
Requires-Python: <4,>=3.9
Requires-Dist: rich-argparse<2,>=1.4.0
Requires-Dist: rich<14,>=13.7.1
